plumlightpad/__init__.py
plumlightpad/lightpad.py
plumlightpad/logicalload.py
plumlightpad/plumcloud.py
plumlightpad/plumdiscovery.py
plumlightpad/plumlightpad.py
plumlightpad-0.0.11.dist-info/METADATA
plumlightpad-0.0.11.dist-info/RECORD
plumlightpad-0.0.11.dist-info/WHEEL
plumlightpad-0.0.11.dist-info/top_level.txt
